LICENSE
setup.py
fap.egg-info/PKG-INFO
fap.egg-info/SOURCES.txt
fap.egg-info/dependency_links.txt
fap.egg-info/top_level.txt
modules/__init__.py
modules/main.py