Metadata-Version: 2.1
Name: fap
Version: 0.0.4
Summary: Apis
Author: sahil
Author-email: sahilapte1@gmail.com
Keywords: fastapi,deeplearning,keras,yolov5,sahil,segmentation
Classifier: Development Status :: 1 - Planning
Classifier: Intended Audience :: Developers
Classifier: Programming Language :: Python :: 3
Classifier: Operating System :: Unix
Classifier: Operating System :: MacOS :: MacOS X
Classifier: Operating System :: Microsoft :: Windows
License-File: LICENSE
